terence/__init__.py
terence/client.py
terence/utils.py
terence-1.0.6.dist-info/licenses/LICENSE
terence-1.0.6.dist-info/METADATA
terence-1.0.6.dist-info/WHEEL
terence-1.0.6.dist-info/top_level.txt
terence-1.0.6.dist-info/RECORD
