Metadata-Version: 2.4
Name: terence
Version: 1.0.6
Summary: Terence is a Python package that makes it easy to scan and analyze GitHub repositories. It simplifies the GitHub API and processes the repo contents into a simple flat dictionary that can be accessed by file path.
Home-page: https://github.com/GarfieldFluffJr/Terence
Author: GarfieldFluffJr
Author-email: louieyin6@gmail.com
Keywords: github api repository scanner code-analysis git python content decode
Classifier: Development Status :: 3 - Alpha
Classifier: Intended Audience :: Developers
Classifier: License :: OSI Approved :: MIT License
Classifier: Operating System :: OS Independent
Classifier: Programming Language :: Python :: 3
Classifier: Programming Language :: Python :: 3.8
Classifier: Programming Language :: Python :: 3.9
Classifier: Programming Language :: Python :: 3.10
Classifier: Programming Language :: Python :: 3.11
Classifier: Topic :: Software Development :: Libraries :: Python Modules
Classifier: Topic :: Software Development :: Version Control :: Git
Requires-Python: >=3.8
License-File: LICENSE
Requires-Dist: PyGithub>=2.1.1
Requires-Dist: python-dotenv>=1.0.0
Provides-Extra: dev
Requires-Dist: pytest>=7.4.0; extra == "dev"
Dynamic: author
Dynamic: author-email
Dynamic: classifier
Dynamic: description
Dynamic: description-content-type
Dynamic: home-page
Dynamic: keywords
Dynamic: license-file
Dynamic: provides-extra
Dynamic: requires-dist
Dynamic: requires-python
Dynamic: summary
